udata_event_service/__init__.py
udata_event_service/consumer.py
udata_event_service/producer.py
udata_event_service-0.0.8.dist-info/LICENSE
udata_event_service-0.0.8.dist-info/WHEEL
udata_event_service-0.0.8.dist-info/METADATA
udata_event_service-0.0.8.dist-info/RECORD
