Metadata-Version: 2.1
Name: udata_event_service
Version: 0.0.8
Summary: udata event service package containing kafka utils
Author-email: Etalab <info@data.gouv.fr>
Classifier: License :: OSI Approved :: MIT License
Requires-Dist: kafka-python==2.0.2
Project-URL: Home, https://www.data.gouv.fr
